{
    "run_name": "dark-blaze-8_2026-03-24_01-53-42",
    "wandb_run_name": "dark-blaze-8",
    "timestamp": "2026-03-24_01-53-42",
    "dataset_info": {
        "dataset_name": "DMN-only Schaefer 46-node (60/20/20 subject-level split)",
        "kNN_param": 8,
        "correlation_type": "z_transformed",
        "num_features": 46,
        "train_dataset_size": 447,
        "val_dataset_size": 92,
        "test_dataset_size": 59,
        "batch_size": 64
    },
    "model_config": {
        "model_type": "GraphAttentionAutoencoderConditioned",
        "in_features": 46,
        "hidden_size": 46,
        "latent_dim": 32,
        "attention_heads": 2,
        "device": "cuda",
        "dropout": 0.5
    },
    "training_config": {
        "batch_size": 64,
        "learning_rate": 0.001,
        "adj_loss_weight": 0.1,
        "epochs": 1000,
        "early_stopping_patience": 100
    }
}